RADO/RADO.py
RADO/__init__.py
scRADO-1.3.dist-info/LICENSE
scRADO-1.3.dist-info/METADATA
scRADO-1.3.dist-info/WHEEL
scRADO-1.3.dist-info/top_level.txt
scRADO-1.3.dist-info/RECORD
