Metadata-Version: 2.1
Name: scRADO
Version: 1.3
Summary: doublet detection algorithm for droplet-based single-cell sequencing data
Home-page: https://github.com/poseidonchan/RADO
Author: Yanshuo Chen
Author-email: poseidonchan@icloud.com
License: MIT License
Platform: any
Requires-Python: >=3.7.1,<3.8
License-File: LICENSE
Requires-Dist: torch (==1.13.1)
Requires-Dist: numpy (==1.21.6)
Requires-Dist: anndata (==0.8.0)
Requires-Dist: scanpy (==1.9.3)
Requires-Dist: anndata (>=0.7.6)
Requires-Dist: tqdm (==4.65.0)
Requires-Dist: scikit-learn (==1.0.2)
